{
    "plugins": [
        {
            "name": "ResizeX",
            "author": "Anxeal",
            "description": "Lets you resize videos and images",
            "url": "https://raw.githubusercontent.com/Anxeal/BDEnhancements/master/plugins/ResizeX.plugin.js"
        },
        {
            "name": "p.complete",
            "author": "XFox Prower",
            "description": "p.complete is a BetterDiscord plugin that gives you IRC-style auto-completion on nicknames.",
            "url": "https://raw.githubusercontent.com/XFoxPrower/p.complete/master/p.complete.plugin.js"
        },
        {
            "name": "Latex Plugin",
            "author": "Mitchell",
            "description": "A really crappy latex embedder. Converts code between $$ into latex. click to expand",
            "url": "http://megamit.github.io/repository/tex/tex.plugin.js"
        },
        {
            "name": "LazyLoad Patcher v1.0",
            "author": "HoLLy",
            "description": "For use with themes that change the size of elements that are lazily loaded.",
            "url": "https://raw.githubusercontent.com/HoLLy-HaCKeR/BetterDiscord-Themes-and-Plugins/master/Plugins/lazyload_patcher.plugin.js"
        },
        {
            "name": "Full Size Lightbox",
            "author": "Jiiks",
            "description": "Show full sized images in image preview",
            "url": "https://gist.githubusercontent.com/Jiiks/7eb81b8950c073a09fbc2493da3ec714/raw/249f01f981a9a6a14bfbd170f28b8bf0e0a540d3/fullSizeLightbox.plugin.js"
        },
        {
            "name": "Hashtag Plugin",
            "author": "Arashiryuu",
            "description": "Simply use the hash symbol '#' at the start of your word or sentence to get a distinct hashtag.",
            "url": "https://raw.githubusercontent.com/Arashiryuu/crap/master/hashTagging.plugin.js"
        },
        {
            "name": "orangeText Plugin",
            "author": "Arashiryuu",
            "description": "Use a less-than symbol '<' at the end of a sentence to make text orange.",
            "url": "https://raw.githubusercontent.com/Arashiryuu/crap/master/orangeTexting.plugin.js"
        },
        {
            "name": "greenText Plugin",
            "author": "Arashiryuu",
            "description": "Use a greater-than symbol '>' at the beginning of a sentence to make text green.",
            "url": "https://raw.githubusercontent.com/Arashiryuu/crap/master/greenText.plugin.js"
        },
        {
            "name": "Transparency Patcher v2.1",
            "author": "HoLLy",
            "description": "Patches your Discord client to allow transparent themes.\nTo use, go to the plugin's settings, press the button, restart Discord COMPLETELY by closing it and re-opening it, then reload by pressing CTRL+R to enable transparency. If transparency is not working, just reload again.\nNOTE: Not giving support, don't mention me for this. If something doesn't work, check the instructions again.",
            "url": "https://raw.githubusercontent.com/HoLLy-HaCKeR/BetterDiscord-Themes-and-Plugins/master/Plugins/transparency_patcher.plugin.js"
        },
        {
            "name": "spoilerAlert",
            "author": "LuaTenshi",
            "description": "Allows you to hide your text as a spoiler by adding \"!!\" to the very start of your message.",
            "url": "https://gist.githubusercontent.com/LuaTenshi/c43c220d1cadd7af4ab8734daf7a6706/raw/4b2c5a5acee5a5e570a83995772f2b4149ea1238/spoilerAlert.plugin.js"
        },
        {
            "name": "BetterCustomCSS",
            "author": "kosshi",
            "description": "Lets you edit CSS live with your favorite text editor. Like Custom CSS but better.",
            "url": "https://raw.githubusercontent.com/kosshishub/BetterCustomCSS-BD-plugin/master/BetterCustomCSS.plugin.js"
        },
        {
            "name": "Snow",
            "author": "Jiiks",
            "description": "Snow",
            "url": "https://i.do.not.care/snoow.plugin.js"
        },
        {
            "name": "Quoter",
            "author": "samogot",
            "description": "Reply to people with a button, quoting full message or selected text",
            "url": "https://gist.githubusercontent.com/samogot/774d3d2059402d5173a72524e39dd7d0/raw/c0f2cd7ebea51a8432d43bdbcd8f2ab94cda96f3/quouter.plugin.js"
        },
        {
            "name": "ReturnScroll",
            "author": "samogot",
            "description": "Button for counting unread messages",
            "url": "https://gist.githubusercontent.com/samogot/026e8894684cd76839c786910192aabd/raw/eb6848d53e8c203ef7ab3b7c624b6d0c5ff47374/return-scroll.plugin.js"
        },
        {
            "name": "CountUnread",
            "author": "samogot",
            "description": "Button for returning to previous scroll position after posting a message",
            "url": "https://gist.githubusercontent.com/samogot/355ba0ff414a6a9551baff500b1af60e/raw/4251658b52b9591ea6bbd38e1a5309ffd101e266/count-unread.plugin.js"
        },
        {
            "name": "High-Quality Avatars",
            "author": "noodlebox",
            "description": "Use crisp, high-resolution versions of avatars everywhere.",
            "url": "https://raw.githubusercontent.com/noodlebox/betterdiscord-plugins/master/HDAvatars.plugin.js"
        },
        {
            "name": "Static Avatars",
            "author": "noodlebox",
            "description": "Don't animate avatars in the chat area.",
            "url": "https://raw.githubusercontent.com/noodlebox/betterdiscord-plugins/master/StaticAvatars.plugin.js"
        },
        {
            "name": "Toggle All",
            "author": "Zerthox",
            "description": "Enable/Disable all plugins or themes with a button",
            "url": "https://raw.githubusercontent.com/Zerthox/BetterDiscord-Plugins/master/plugins/ToggleAll.plugin.js"
        },
        {
            "name": "Theme Customizer",
            "author": "Zerthox",
            "description": "Customize CSS variables of themes",
            "url": "https://raw.githubusercontent.com/Zerthox/BetterDiscord-Plugins/master/plugins/ThemeCustomizer.plugin.js"
        },
        {
            "name": "EvenBetterDiscord",
            "author": "DeathStrikeV",
            "description": "Loads FFZ emotes from alternate repository",
            "url": "https://raw.githubusercontent.com/DeathStrikeV/EvenBetterDiscord/master/EvenBetterDiscord.plugin.js"
        },
        {
            "name": "Line Numbers",
            "author": "noodlebox",
            "description": "Add line numbers to code blocks.",
            "url": "https://raw.githubusercontent.com/noodlebox/betterdiscord-plugins/master/LineNumbers.plugin.js"
        },
        {
            "name": "Kawaii Emotes",
            "author": "noodlebox",
            "description": "Better emote parsing for BetterDiscord. Fixes bugs with emotes and tooltips.",
            "url": "https://raw.githubusercontent.com/noodlebox/betterdiscord-plugins/master/KawaiiEmotes.plugin.js"
        },
        {
            "name": "BetterDiscord Beta Test",
            "author": "Jiiks",
            "description": "Enables certain beta features before they're implemented to BetterDiscord",
            "url": "https://gist.githubusercontent.com/Jiiks/cd0ae9195ff42f0e79024170cb747e91/raw/betas.plugin.js"
        },
        {
            "name": "Server Themes",
            "author": "DeNial",
            "description": "Allow individual servers to use specific themes.  More instructions on repo: https://github.com/IRDeNial/BD-Server-Themes/blob/master/README.md",
            "url": "https://raw.githubusercontent.com/IRDeNial/BD-Server-Themes/master/serverTheme.plugin.js"
        },
        {
            "name": "Creation Date",
            "author": "Natsulus",
            "description": "See when a user's account was created.",
            "url": "https://raw.githubusercontent.com/Natsulus/BD-Repo/master/plugins/Creation%20Date/CreationDate.plugin.js"
        },
        {
            "name": "Hide Images",
            "author": "Anxeal",
            "description": "Adds a button to the right-click menu to hide images on certain servers and channels",
            "url": "https://raw.githubusercontent.com/Anxeal/BDEnhancements/master/plugins/HideImages.plugin.js"
        },
        {
            "name": "Colored Typing",
            "author": "Anxeal, Bolli",
            "description": "Make the text color of the \"typing...\" text same as role color",
            "url": "https://raw.githubusercontent.com/Anxeal/BDEnhancements/master/plugins/ColoredTyping.plugin.js"
        },
        {
            "name": "Colored Voice",
            "author": "Anxeal",
            "description": "Make the text color of the names in the voice channel same as role color",
            "url": "https://raw.githubusercontent.com/Anxeal/BDEnhancements/master/plugins/ColoredVoice.plugin.js"
        },
        {
            "name": "Renamer",
            "author": "Mitchell",
            "description": "Give anyone a nickname that only you can see simply by right clicking on them.",
            "url": "https://gist.githubusercontent.com/megamit/7a686742c2768f34cf4d83e1055e9375/raw/renamer.plugin.js"
        }, 
        {
            "name": "Copy Code",
            "author": "Finicalmist",
            "description": "Copies Code from Code Blocks with a Button",
            "url": "https://raw.githubusercontent.com/Finicalmist/CopyCode/master/copyCode.plugin.js"
        }, 
        {
            "name": "Better Plugin Repo",
            "author": "samfun123",
            "description": "A upgraded plugin repository for #plugin-repo. A preview of it here: https://imgur.com/8fAgy1Y Update: Made installation happen automatically. (Not to be affiliated with EvenBetterRepo)",
            "url": "https://raw.githubusercontent.com/samfun123/script-storage/master/betterdiscord/plugins/betterRepo.plugin.js"
        },
        {
            "name": "Channel Collapse Button",
            "author": "IRDeNial",
            "description": "Create a button that allows for hiding of channel list",
            "url": "https://raw.githubusercontent.com/IRDeNial/discord-channel-collapse-button/master/channelcollapsebutton.plugin.js"
        }, 
        {
            "name": "Autoplay GIF and GIFV",
            "author": "noodlebox",
            "description": "Automatically play GIF and GIFV embeds and Nitro avatars without having to hover.",
            "url": "https://raw.githubusercontent.com/noodlebox/betterdiscord-plugins/master/AutoPlayGifs.plugin.js"
        }, 
        {
            "name": "Custom role colour",
            "author": "Jiiks, Pohky",
            "description": "Set any colour as role colour",
            "url": "https://raw.githubusercontent.com/Jiiks/BetterDiscordApp/master/Plugins/customRoleColour.plugin.js"
        }, 
        {
            "name": "Media Support",
            "author": "Jiiks",
            "description": "Add support for html5 media",
            "url": "https://raw.githubusercontent.com/Jiiks/BetterDiscordApp/master/Plugins/mediaSupport.plugin.js"
        }, 
        {
            "name": "Server/Channel Sorter",
            "author": "CosmicSalad",
            "description": "Drag and Drop to reorder the list of servers and channels",
            "url": "https://raw.githubusercontent.com/cosmicsalad/Discord-Themes-and-Plugins/master/plugins/sorter.plugin.js"
        }, 
        {
            "name": "Avatar hover",
            "author": "noVaLue",
            "description": "When hovering, show a resized version of the avatar. Use Ctrl / Ctrl+Shift",
            "url": "https://raw.githubusercontent.com/iVEnoVaLue/BetterPlugins/master/plugins/avatar.plugin.js"
        }, 
        {
            "name": "Double click edit",
            "author": "Jiiks",
            "description": "Double click your messages to edit them - quite hacky",
            "url": "https://raw.githubusercontent.com/Jiiks/BetterDiscordApp/master/Plugins/dblClickEdit.plugin.js"
        }, 
        {
            "name": "Emote Blacklist",
            "author": "Jiiks",
            "description": "Blacklist emotes you don't want to see",
            "url": "https://raw.githubusercontent.com/Jiiks/BetterDiscordApp/master/Plugins/emoteBlacklist.plugin.js"
        },
        {
            "name": "Digital Clock",
            "author": "Jiiks",
            "description": "Add a clock to your client. Use the #clockPluginClock selector to style it yourself",
            "url": "https://raw.githubusercontent.com/Jiiks/BetterDiscordApp/master/Plugins/clock.plugin.js"
        }, 
        {
            "name": "Replyer",
            "author": "Hammock",
            "description": "@ Reply someone with a button",
            "url": "https://raw.githubusercontent.com/cosmicsalad/Discord-Themes-and-Plugins/master/plugins/replyer.plugin.js"
        }, 
        {
            "name": "Collapsible Embeds",
            "author": "shtrih",
            "description": "Creates caret to hide image/video previews near each link",
            "url": "https://gist.githubusercontent.com/shtrih/59a8be1f9ff53f0499c2/raw/CollapsibleEmbeds.plugin.js"
        },
        {
            "name": "EmbedAV",
            "author": "shtrih",
            "description": "Creates <video> or <audio> for links and attachments.",
            "url": "https://gist.githubusercontent.com/shtrih/8a72a36d513ec704c7a9/raw/EmbedAV.plugin.js"
        },
        {
            "name": "CompactGuilds",
            "author": "Kosshi",
            "description": "Reduces sidebar's width or hides it completetly by displaying it only when cursor is near left edge.",
            "url": "https://raw.githubusercontent.com/kosshishub/CompactGuilds-BD-plugin/master/CompactGuilds.plugin.js"
        },
        {
            "name": "Quicksave",
            "author": "Kosshi",
            "description": "Lets you save images fast with a short random name (Or the original if you want to)",
            "url": "https://raw.githubusercontent.com/kosshishub/Quicksave-BD-plugin/master/Quicksave.plugin.js"
        }, 
        {
            "name": "Fave Emote Sorter",
            "author": "Hammock",
            "description": "Drag & Drop rearrange your list of favourited emotes",
            "url": "https://raw.githubusercontent.com/cosmicsalad/Discord-Themes-and-Plugins/master/plugins/emoteSorter.plugin.js"
        },  
        {
            "name": "detTube",
            "author": "megamit",
            "description": "Deatch youtube to make it moveable",
            "url": "https://gist.githubusercontent.com/megamit/29757d819de5356595271cebb577f6a8/raw/DetachableYoutube.plugin.js" 
        },
        {
            "name": "Switcher Plugin",
            "author": "Ciaran",
            "description": "Switch channels quickly via the keyboard. Just press ctrl+k",
            "url": "https://raw.githubusercontent.com/ciaran/bd-switcher/master/switcher.plugin.js"
        },
        {
            "name": "Search Plugin",
            "author": "megamit",
            "description": "The return of ctrl+f!  Until at least discord devs decide to add it",
            "url": "https://gist.githubusercontent.com/megamit/a676acb2f34b201e364858aca299fb44/raw/search.plugin.js"
        },
        {
            "name": "Direct Media Converter",
            "author": "samfun123",
            "description": "Tries to convert most direct image links to embedded images.",
            "url": "https://raw.githubusercontent.com/samfun123/script-storage/master/betterdiscord/plugins/directMedia.plugin.js"
        }, 
        {
            "name": "Automatic Link Unshortener",
            "author": "samfun123",
            "description": "Checks for common link shorteners and converts them to the original link.",
            "url": "https://raw.githubusercontent.com/samfun123/script-storage/master/betterdiscord/plugins/unshortenLinks.plugin.js"
        },
        {
            "name": "Owner Tags",
            "author": "noodlebox",
            "description": "Show a tag next to a server owner's name.",
            "url": "https://raw.githubusercontent.com/noodlebox/betterdiscord-plugins/master/OwnerTag.plugin.js"
        }, 
        {
            "name": "MorkMoji",
            "author": "MorkHub",
            "description": "Enlarges emoji in messages to 64px (or custom size configurable in settings panel)",
            "url": "https://raw.githubusercontent.com/MorkHub/BetterDiscord-MorkMoji/master/morkMoji.plugin.js"
        }
    ],
    "themes": [
        {
            "name": "Minimal Tweaks 1.0",
            "author": "HoLLy",
            "description": "A theme that makes minimal mode more minimal (and fixes some bugs). Requires the LazyLoad Patcher Plugin",
            "url": "https://raw.githubusercontent.com/HoLLy-HaCKeR/BetterDiscord-Themes-and-Plugins/master/Themes/MinimalTweaks.theme.css",
            "preview": "https://camo.githubusercontent.com/417f596227e26c28a8d30b0c650ba48650e0d5e1/687474703a2f2f692e696d6775722e636f6d2f436a6c674a46362e706e67"
        },
        {
            "name": "Chat Text Bubbles",
            "author": "maple",
            "description": "Stylize your clients chat messages to look like mobile text messages with the Chat Text Bubbles! (Works on top of most themes too)",
            "url": "https://raw.githubusercontent.com/mrmaple240/ChatTextBubbles/master/ChatTextBubbles.theme.css",
            "preview": "https://camo.githubusercontent.com/1cef8e7c304e236bbbf2405826f42d401f473e34/687474703a2f2f692e696d6775722e636f6d2f504b47557a336a2e706e67"
        },
        {
            "name": "JustBlack",
            "author": "Dddsasul",
            "description": "A very dark theme mostly black with a little very dark grays",
            "url": "https://raw.githubusercontent.com/Dddsasul/TeamKappa-theme/master/JustBlack.theme.css",
            "preview": "https://camo.githubusercontent.com/25f46a9c10b6ddea7774eb7f2263f6877b37b4cf/68747470733a2f2f692e6779617a6f2e636f6d2f63303732653737363833623766643366623836366366636631316534363263662e706e67"
        },
        {
            "name": "Transparency 1.0",
            "author": "HoLLy",
            "description": "A theme that takes advantage of the transparency patch I made. It can also be used as base for a simple background theme.\nNo support will be given for the transparency patch.",
            "url": "https://raw.githubusercontent.com/HoLLy-HaCKeR/BetterDiscord-Themes-and-Plugins/master/Themes/Transparency.theme.css",
            "preview": "https://camo.githubusercontent.com/0f0b6dea1101149b86e5fdb6a055cdefdfb1d479/68747470733a2f2f692e696d6775722e636f6d2f436d676f7030762e706e67"
        },
        {
            "name": "Popouts Upgraded",
            "author": "maple",
            "description": "Adds a growing backdrop to popouts and stylized User Popouts.",
            "url": "https://raw.githubusercontent.com/mrmaple240/Popouts-Upgraded/master/PopoutsUpgraded.theme.css",
            "preview": "https://camo.githubusercontent.com/f1c8b29d6cc18b618a001084db75f8a404463c88/68747470733a2f2f6d792e6d6978746170652e6d6f652f726d706b6b622e676966"
        },
        {
            "name": "UserPopouts Upgraded",
            "author": "maple",
            "description": "Stylized User Popouts.",
            "url": "https://raw.githubusercontent.com/mrmaple240/UserPopoutUpgraded/master/UserPopoutsUpgraded.theme.css",
            "preview": "https://camo.githubusercontent.com/3559de4408e194d62a18fb09bea34c13327c799a/68747470733a2f2f6d792e6d6978746170652e6d6f652f676265716b682e676966"
        },
        {
            "name": "Full Dark theme",
            "author": "fluffy",
            "description": "A theme which aims to complete the dark theme for Discord! All elements that were previously white and bright are now in full dark goodness.",
            "url": "https://raw.githubusercontent.com/fluffingtons/fulldark/master/fulldark.theme.css",
            "preview": "https://raw.githubusercontent.com/fluffingtons/fulldark/resources/documents/screenshots/screenshot1.png"
        },
        {
            "name": "Spoiler CSS",
            "author": "Pu",
            "description": "CSS for hiding content marked as spoiler, that will show only on hover.\nUsage: ***Spoiler***\nWarning: Only people with this css won't see the spoiler, people without it will see normal text!",
            "url": "https://raw.githubusercontent.com/Puv1s/Discord-Spoiler/master/Spoiler_Tag.theme.css",
            "preview": ""
        },
        {
            "name": "Dark Cyan (Flat & Edgy)",
            "author": "マギルゥーベルベット (magiruuvelvet)",
            "description": "A dark cyan and flat & edgy theme for Discord",
            "url": "https://raw.githubusercontent.com/magiruuvelvet/discord-theme-dark-cyan-flat-edgy/master/dark-cyan-flat-edgy.theme.css",
            "preview": "https://raw.githubusercontent.com/magiruuvelvet/discord-theme-dark-cyan-flat-edgy/master/screenshots/main-ui.png"
        },
        {
            "name": "Kobato",
            "author": "Syaoran3",
            "description": "A Kobato theme made for EternalEnd",
            "url": "https://raw.githubusercontent.com/DRedDogPE/DiscordThemes/master/Kobato/Kobato.theme.css"
        },
        {
            "name": "Full Dark",
            "author": "fluffingtons",
            "description": "A theme which aims to complete the dark theme for Discord.",
            "url": "https://raw.githubusercontent.com/fluffingtons/fulldark/master/fulldark.theme.css"
        },
        {
            "name": "Material Icons Theme",
            "author": "Zerthox",
            "description": "A theme for Discord changing icons",
            "url": "https://raw.githubusercontent.com/Zerthox/Material-Icon-Theme/master/Material_Icon.theme.css"
        },
        {
            "name": "Wheat Transparency",
            "author": "Zekeeh",
            "description": "Wheat Transparency theme for Discord",
            "url": "https://raw.githubusercontent.com/Zekeeh/Wheat-Transparency/master/WheatTransparency.theme.css"
        },
        {
            "name": "Titlebar",
            "author": "BeardDesign",
            "description": "Add a titlebar to the top of your window :)",
            "url": "https://raw.githubusercontent.com/BeardDesign1/Titlebar/master/Titlebar.theme.css",
            "preview": ""
        },
        {
            "name": "Discord Reborn",
            "author": "Omniscient",
            "description": "",
            "url": "https://raw.githubusercontent.com/0mniscient/Discord-Themes/master/Themes/Discord%20Reborn.theme.css",
            "preview": ""
        },
        {
            "name": "Discordify",
            "author": "Nirewen",
            "description": "",
            "url": "https://gist.githubusercontent.com/nirewen/a2078af9a41943ab19cf50e2944d1ca9/raw/Discordify.theme.css",
            "preview": ""
        }, 
        {
            "name": "Dark Souls",
            "author": "Satan/Mondanzo",
            "description": "",
            "url": "https://raw.githubusercontent.com/Mondanzo/GameThemes-BetterDiscord/master/dark_souls.theme.css",
            "preview": ""
        }, 
        {
            "name": "Simplistic CSS",
            "author": "den",
            "description": "Dubai Orange",
            "url": "https://raw.githubusercontent.com/denBot/Simplistic-CSS/master/DubaiOrange.theme.css",
            "preview": ""
        }, 
        {
            "name": "Simplistic CSS",
            "author": "den",
            "description": "Green Transparent",
            "url": "https://raw.githubusercontent.com/denBot/Simplistic-CSS/master/Green.theme.css",
            "preview": ""
        }, 
        {
            "name": "Simplistic CSS",
            "author": "den",
            "description": "Maware Shade",
            "url": "https://raw.githubusercontent.com/denBot/Simplistic-CSS/master/MawaresShade.theme.css",
            "preview": ""
        }, 
        {
            "name": "Simplistic CSS",
            "author": "den",
            "description": "Oceanic Blue",
            "url": "https://raw.githubusercontent.com/denBot/Simplistic-CSS/master/OceanicBlue.theme.css",
            "preview": ""
        }, 
        {
            "name": "Simplistic CSS",
            "author": "den",
            "description": "Vibrant Pink",
            "url": "https://raw.githubusercontent.com/denBot/Simplistic-CSS/master/Pink.theme.css",
            "preview": ""
        }, 
        {
            "name": "Simplistic CSS",
            "author": "den",
            "description": "Simplistic Blue",
            "url": "https://raw.githubusercontent.com/denBot/Simplistic-CSS/master/Simplified-Blue.theme.css",
            "preview": ""
        }, 
        {
            "name": "Simplistic CSS",
            "author": "den",
            "description": "Simplistic Green",
            "url": "https://raw.githubusercontent.com/denBot/Simplistic-CSS/master/Simplified-Green.theme.css",
            "preview": ""
        }, 
        {
            "name": "OriginalModern",
            "author": "mat3",
            "description": "",
            "url": "https://raw.githubusercontent.com/mathiaslsn/OriginalModern/master/mat.theme.css",
            "preview": ""
        }, 
        {
            "name": "IOS Switches",
            "author": "BeardDesign",
            "description": "Use IOS switches instead of checkboxes",
            "url": "https://raw.githubusercontent.com/BeardDesign1/Ios-switches/themes/IOS_Switches.theme.css",
            "preview": ""
        }, 
        {
            "name": "Cyan Firewatch",
            "author": "den",
            "description": "",
            "url": "https://raw.githubusercontent.com/denBot/Cyan-Firewatch/master/cyan-firewatch.theme.css",
            "preview": ""
        }, 
        {
            "name": "Modal Animations",
            "author": "BeardDesign",
            "description": "Animation 1",
            "url": "https://raw.githubusercontent.com/BeardDesign1/discord-modal-animations/themes/modal-anim-1.theme.css",
            "preview": ""
        }, 
        {
            "name": "Modal Animations",
            "author": "BeardDesign",
            "description": "Animation 2",
            "url": "https://raw.githubusercontent.com/BeardDesign1/discord-modal-animations/themes/modal-anim-2.theme.css",
            "preview": ""
        }, 
        {
            "name": "Modal Animations",
            "author": "BeardDesign",
            "description": "Animation 3",
            "url": "https://raw.githubusercontent.com/BeardDesign1/discord-modal-animations/themes/modal-anim-3.theme.css",
            "preview": ""
        }, 
        {
            "name": "Modal Animations",
            "author": "BeardDesign",
            "description": "Animation 4",
            "url": "https://raw.githubusercontent.com/BeardDesign1/discord-modal-animations/themes/modal-anim-4.theme.css",
            "preview": ""
        }, 
        {
            "name": "Modal Animations",
            "author": "BeardDesign",
            "description": "Animation 5",
            "url": "https://raw.githubusercontent.com/BeardDesign1/discord-modal-animations/themes/modal-anim-5.theme.css",
            "preview": ""
        }, 
        {
            "name": "Modal Animations",
            "author": "BeardDesign",
            "description": "Animation 6",
            "url": "https://raw.githubusercontent.com/BeardDesign1/discord-modal-animations/themes/modal-anim-6.theme.css",
            "preview": ""
        }, 
        {
            "name": "Modal Animations",
            "author": "BeardDesign",
            "description": "Animation 7",
            "url": "https://raw.githubusercontent.com/BeardDesign1/discord-modal-animations/themes/modal-anim-7.theme.css",
            "preview": ""
        }, 
        {
            "name": "Modal Animations",
            "author": "BeardDesign",
            "description": "Animation 8",
            "url": "https://raw.githubusercontent.com/BeardDesign1/discord-modal-animations/themes/modal-anim-8.theme.css",
            "preview": ""
        }, 
        {
            "name": "Material Design Switches",
            "author": "BeardDesign",
            "description": "Material design switches instead of checkboxes",
            "url": "https://raw.githubusercontent.com/BeardDesign1/Material-design-switches/themes/Material_Switches.theme.css",
            "preview": ""
        }, 
        {
            "name": "MinimaCord",
            "author": "gustarrini",
            "description": "",
            "url": "https://raw.githubusercontent.com/gustarrini/MinimaCord/master/minimacordloader.theme.css",
            "preview": ""
        }, 
        {
            "name": "Modern N' Cozy",
            "author": "Narugokyu",
            "description": "",
            "url": "https://raw.githubusercontent.com/Narugokyu/modern-n-cozy/master/modern-n-cozy.theme.css",
            "preview": ""
        }, 
        {
            "name": "Small Members Tab",
            "author": "BeartDesign",
            "description": "",
            "url": "https://raw.githubusercontent.com/BeardDesign1/small-members-tab/themes/small-members-tab.theme.css",
            "preview": ""
        }, 
        {
            "name": "ClearVision Amber",
            "author": "Zerthox",
            "description": "A fiery, orange theme with customizable colors & background",
            "url": "https://raw.githubusercontent.com/Zerthox/ClearVision/master/themes/ClearVision_Amber.theme.css",
            "preview": "https://cdn.rawgit.com/Zerthox/ClearVision/master/screenshots/amber1.png"
        }, 
        {
            "name": "ClearVision Amethyst",
            "author": "Zerthox",
            "description": "A mystical, purple theme with customizable colors & background",
            "url": "https://raw.githubusercontent.com/Zerthox/ClearVision/master/themes/ClearVision_Amethyst.theme.css",
            "preview": "https://cdn.rawgit.com/Zerthox/ClearVision/master/screenshots/amethyst1.png"
        }, 
        {
            "name": "ClearVision Emerald",
            "author": "Zerthox",
            "description": "A peaceful, green theme with customizable colors & background",
            "url": "https://raw.githubusercontent.com/Zerthox/ClearVision/master/themes/ClearVision_Emerald.theme.css",
            "preview": "https://cdn.rawgit.com/Zerthox/ClearVision/master/screenshots/emerald1.png"
        }, 
        {
            "name": "ClearVision Ruby",
            "author": "Zerthox",
            "description": "A raging, red theme with customizable colors & background",
            "url": "https://raw.githubusercontent.com/Zerthox/ClearVision/master/themes/ClearVision_Ruby.theme.css",
            "preview": "https://cdn.rawgit.com/Zerthox/ClearVision/master/screenshots/ruby1.png"
        }, 
        {
            "name": "ClearVision Sapphire",
            "author": "Zerthox",
            "description": "A chilly, blue theme with customizable colors & background",
            "url": "https://raw.githubusercontent.com/Zerthox/ClearVision/master/themes/ClearVision_Sapphire.theme.css",
            "preview": "https://cdn.rawgit.com/Zerthox/ClearVision/master/screenshots/sapphire1.png"
        }, 
        {
            "name": "Akame",
            "author": "llcoll",
            "description": "",
            "url": "https://raw.githubusercontent.com/llcoll/Discord-Themes/master/Themes/Akame/Akame.theme.css",
            "preview": ""
        }, 
        {
            "name": "Overwatch",
            "author": "Matt",
            "description": "",
            "url": "https://raw.githubusercontent.com/Matthaz/Overwatch_theme/master/Overwatch.theme.css",
            "preview": ""
        }, 
        {
            "name": "Shiny Octo Waffle",
            "author": "Kappa123",
            "description": "",
            "url": "https://raw.githubusercontent.com/PepeLUL/Shiny-Octo-Waffle-Theme/master/Shiny.theme.css",
            "preview": ""
        }, 
        {
            "name": "Beard's Material Theme",
            "author": "BeardDesign",
            "description": "http://www.beard-design.com/discord-material-theme.html",
            "url": "https://raw.githubusercontent.com/BeardDesign1/Material-design-theme/themes/Beard's-Material-theme-for-Discord.theme.css",
            "preview": ""
        }, 
        {
            "name": "Esdeath",
            "author": "llcoll",
            "description": "",
            "url": "https://raw.githubusercontent.com/llcoll/Discord-Themes/master/Themes/Esdeath/Esdeath.theme.css",
            "preview": ""
        }, 
        {
            "name": "Space Nova",
            "author": "Narugokyu",
            "description": "",
            "url": "https://raw.githubusercontent.com/Narugokyu/nova-theme/master/space_nova.theme.css",
            "preview": ""
        }, 
        {
            "name": "Re:Zero",
            "author": "TimcanpyCC",
            "description": "",
            "url": "https://raw.githubusercontent.com/CurimuChizu/CC-Themes/master/CC-Themes/ReZero.theme.css",
            "preview": ""
        }, 
        {
            "name": "Witcher 3",
            "author": "Jadeonking",
            "description": "",
            "url": "https://raw.githubusercontent.com/jadeonking/WitcherCord/master/Themes/Witcher3.theme.css",
            "preview": ""
        },
        {   "name": "DuskCord",
            "author": "Jadeonking",
            "description": "",
            "url": "https://raw.githubusercontent.com/jadeonking/WitcherCord/master/Themes/DuskCord.theme.css",
            "preview": ""
        },
        {
            "name": "Dat Discord",
            "author": "IceCleaver",
            "description": "",
            "url": "https://raw.githubusercontent.com/Viniuau/Dat-Discord/master/Dat%20Discord.theme.css",
            "preview": ""
        }, 
        {
            "name": "Full Light",
            "author": "maple",
            "description": "",
            "url": "https://raw.githubusercontent.com/mrmaple240/Full-Light-Theme/master/FullLightTheme.theme.css",
            "preview": ""
        }, 
        {
            "name": "Red n Black",
            "author": "TimcanpyCC",
            "description": "",
            "url": "https://raw.githubusercontent.com/CurimuChizu/CC-Themes/master/CC-Themes/Red.n.Black.theme.css",
            "preview": ""
        }, 
        {
            "name": "Shades of Red",
            "author": "Prominency",
            "description": "",
            "url": "https://raw.githubusercontent.com/trueprominency/Shades-of-Red-Theme/master/shades-of-red.theme.css",
            "preview": ""
        }, 
        {
            "name": "Thin Dark",
            "author": "Snazzah",
            "description": "",
            "url": "https://raw.githubusercontent.com/SnazzyPine25/Better-Discord-Themes/master/Themes/Thin-Dark/ThinDark.theme.css",
            "preview": ""
        }, 
        {
            "name": "Clear Discord",
            "author": "Dddsasul",
            "description": "",
            "url": "https://raw.githubusercontent.com/Dddsasul/TeamKappa-theme/master/ClearDiscord.theme.css",
            "preview": ""
        }, 
        {
            "name": "Casual Dark",
            "author": "Quietness",
            "description": "",
            "url": "https://raw.githubusercontent.com/Quietess/Casual-Dark/master/CasualDark.css",
            "preview": ""
        },
        {
            "name": "Metro For Discord",
            "author": "Tako",
            "description": "",
            "url": "https://raw.githubusercontent.com/TakosThings/Metro-for-Discord/master/Metro_for_Discord.theme.css",
            "preview": ""
        },
        {
            "name": "Battlefield",
            "author": "Tako",
            "description": "",
            "url": "https://raw.githubusercontent.com/TakosThings/battlefield/master/battlefield.theme.css",
            "preview": ""
        }
    ]
}
